MiTemperature/MiTemperature.py
MiTemperature/__init__.py
Newkiton/Newkiton.py
Newkiton/__init__.py
ThermoBeacon/ThermoBeacon.py
ThermoBeacon/__init__.py
tests/__init__.py
tests/test_mitemperature.py
tests/test_newkiton.py
tests/test_thermobeacon.py
AmazonEnviroSensors-0.3.0.dist-info/LICENSE
AmazonEnviroSensors-0.3.0.dist-info/METADATA
AmazonEnviroSensors-0.3.0.dist-info/WHEEL
AmazonEnviroSensors-0.3.0.dist-info/top_level.txt
AmazonEnviroSensors-0.3.0.dist-info/RECORD
