Metadata-Version: 2.1
Name: AmazonEnviroSensors
Version: 0.3.0
Summary: Amazon Environmental sensors
Home-page: https://github.com/diarmuid/AmazonEnviroSensors
Author: Diarmuid Collins
Author-email: diarmuid.m.collins+github@gmail.com
Classifier: Programming Language :: Python :: 3
Classifier: License :: OSI Approved :: MIT License
Classifier: Operating System :: OS Independent
License-File: LICENSE
Requires-Dist: bluepy3
